metarace_roadmeet-1.13.15.dist-info/licenses/LICENSE
roadmeet/__init__.py
roadmeet/__main__.py
roadmeet/drelay.py
roadmeet/irtt.py
roadmeet/rms.py
roadmeet/trtt.py
roadmeet/uiutil.py
roadmeet/ui/__init__.py
roadmeet/ui/irtt.ui
roadmeet/ui/new_start.ui
roadmeet/ui/rms.ui
roadmeet/ui/roadmeet.ui
roadmeet/ui/swap_rider.ui
metarace_roadmeet-1.13.15.dist-info/METADATA
metarace_roadmeet-1.13.15.dist-info/WHEEL
metarace_roadmeet-1.13.15.dist-info/entry_points.txt
metarace_roadmeet-1.13.15.dist-info/top_level.txt
metarace_roadmeet-1.13.15.dist-info/RECORD
